{"_invocation_id": "3e837a09-b489-4830-b797-924965960e7d", "linked": {"0": {"name": "model.lake_analytics.customer_segments", "type": "model"}, "1": {"name": "model.lake_analytics.employee_department_salary_summary", "type": "model"}, "2": {"name": "model.lake_analytics.employee_salary_band", "type": "model", "succ": [1]}, "3": {"name": "model.lake_analytics.employee_manager_summary", "type": "model"}, "4": {"name": "model.lake_analytics.dim_employee", "type": "model", "succ": [3, 5, 2]}, "5": {"name": "model.lake_analytics.employee_role_summary", "type": "model"}, "6": {"name": "model.lake_analytics.customer_profile_features", "type": "model"}, "7": {"name": "model.lake_analytics.stg_customer_profile", "type": "model", "succ": [6]}, "8": {"name": "model.lake_analytics.stg_employee", "type": "model", "succ": [4]}, "9": {"name": "operation.lake_analytics.lake_analytics-on-run-start-0", "type": "operation"}, "10": {"name": "operation.lake_analytics.lake_analytics-on-run-start-1", "type": "operation"}, "11": {"name": "operation.lake_analytics.lake_analytics-on-run-start-2", "type": "operation"}, "12": {"name": "operation.lake_analytics.lake_analytics-on-run-start-3", "type": "operation"}, "13": {"name": "operation.lake_analytics.lake_analytics-on-run-start-4", "type": "operation"}, "14": {"name": "model.lake_analytics.customer_predictions", "type": "model"}}}